setup.py
orgtblfilter/__init__.py
orgtblfilter.egg-info/PKG-INFO
orgtblfilter.egg-info/SOURCES.txt
orgtblfilter.egg-info/dependency_links.txt
orgtblfilter.egg-info/entry_points.txt
orgtblfilter.egg-info/top_level.txt