Metadata-Version: 1.1
Name: orgtblfilter
Version: 0.1
Summary: A sphinx extension to pre-process orgtbl-mode tables to sphinx tables
Home-page: https://github.com/deets/orgtblfilter
Author: Diez B. Roggisch
Author-email: deets@web.de
License: BSD
Keywords: sphinx extension
Platform: UNKNOWN
Classifier: Development Status :: 4 - Beta
Classifier: Environment :: Console
Classifier: Intended Audience :: Developers
Classifier: License :: OSI Approved :: BSD License
Classifier: Programming Language :: Python
Classifier: Topic :: Documentation
Classifier: Topic :: Utilities
Requires: sphinx
